talkops/__init__.py
talkops/attachment.py
talkops/event_bus.py
talkops/extension.py
talkops/image.py
talkops/link.py
talkops/manifest.py
talkops/media.py
talkops/parameter.py
talkops/readme.py
talkops/video.py
talkops/data/categories.json
talkops/data/event-types.json
talkops/data/readme.jinja2
talkops-1.4.0.dist-info/licenses/LICENSE
talkops-1.4.0.dist-info/METADATA
talkops-1.4.0.dist-info/WHEEL
talkops-1.4.0.dist-info/top_level.txt
talkops-1.4.0.dist-info/RECORD
