Metadata-Version: 2.4
Name: talkops
Version: 1.4.0
Summary: TalkOps SDK
Home-page: https://github.com/talkops/sdk-python
Author: PicoUX
License: MIT
Project-URL: Homepage, https://talkops.app
Project-URL: Issues, https://github.com/talkops/sdk-python/issues
Project-URL: Source, https://github.com/talkops/sdk-python
Keywords: sdk
Classifier: Programming Language :: Python :: 3
Classifier: Operating System :: OS Independent
Requires-Python: >=3.9
License-File: LICENSE
Requires-Dist: jinja2
Requires-Dist: nest_asyncio
Dynamic: author
Dynamic: classifier
Dynamic: description
Dynamic: description-content-type
Dynamic: home-page
Dynamic: keywords
Dynamic: license
Dynamic: license-file
Dynamic: project-url
Dynamic: requires-dist
Dynamic: requires-python
Dynamic: summary
